odoo/addons/stock_picking_report_valued/README.rst
odoo/addons/stock_picking_report_valued/__init__.py
odoo/addons/stock_picking_report_valued/__manifest__.py
odoo/addons/stock_picking_report_valued/i18n/es.po
odoo/addons/stock_picking_report_valued/i18n/hr.po
odoo/addons/stock_picking_report_valued/i18n/ja.po
odoo/addons/stock_picking_report_valued/i18n/ja_JP.po
odoo/addons/stock_picking_report_valued/i18n/ja_KS.po
odoo/addons/stock_picking_report_valued/i18n/ro.po
odoo/addons/stock_picking_report_valued/i18n/stock_picking_report_valued.pot
odoo/addons/stock_picking_report_valued/models/__init__.py
odoo/addons/stock_picking_report_valued/models/res_partner.py
odoo/addons/stock_picking_report_valued/models/stock_move_line.py
odoo/addons/stock_picking_report_valued/models/stock_picking.py
odoo/addons/stock_picking_report_valued/readme/CONFIGURE.rst
odoo/addons/stock_picking_report_valued/readme/CONTRIBUTORS.rst
odoo/addons/stock_picking_report_valued/readme/DESCRIPTION.rst
odoo/addons/stock_picking_report_valued/readme/ROADMAP.rst
odoo/addons/stock_picking_report_valued/readme/USAGE.rst
odoo/addons/stock_picking_report_valued/report/stock_picking_report_valued.xml
odoo/addons/stock_picking_report_valued/static/description/icon.png
odoo/addons/stock_picking_report_valued/static/description/index.html
odoo/addons/stock_picking_report_valued/tests/__init__.py
odoo/addons/stock_picking_report_valued/tests/test_stock_picking_valued.py
odoo/addons/stock_picking_report_valued/views/res_partner_view.xml
odoo12_addon_stock_picking_report_valued-12.0.1.0.2.dist-info/METADATA
odoo12_addon_stock_picking_report_valued-12.0.1.0.2.dist-info/WHEEL
odoo12_addon_stock_picking_report_valued-12.0.1.0.2.dist-info/top_level.txt
odoo12_addon_stock_picking_report_valued-12.0.1.0.2.dist-info/RECORD
